quasardb/INSTALL.vcxproj
quasardb/INSTALL.vcxproj.filters
quasardb/__init__.py
quasardb/__init__.pyi
quasardb/cmake_install.cmake
quasardb/firehose.py
quasardb/pool.py
quasardb/qdb_api.dll
quasardb/quasardb.cp311-win_amd64.pyd
quasardb/stats.py
quasardb/table_cache.py
quasardb/typing.py
quasardb/CMakeFiles/generate.stamp
quasardb/CMakeFiles/generate.stamp.depend
quasardb/date/ALL_BUILD.vcxproj
quasardb/date/ALL_BUILD.vcxproj.filters
quasardb/date/INSTALL.vcxproj
quasardb/date/INSTALL.vcxproj.filters
quasardb/date/cmake_install.cmake
quasardb/date/date.sln
quasardb/date/dateConfigVersion.cmake
quasardb/date/dateTargets.cmake
quasardb/date/CMakeFiles/generate.stamp
quasardb/date/CMakeFiles/generate.stamp.depend
quasardb/date/CMakeFiles/Export/df49adab93b9e0c10c64f72458b31971/dateTargets.cmake
quasardb/extensions/__init__.py
quasardb/extensions/writer.py
quasardb/numpy/__init__.py
quasardb/pandas/__init__.py
quasardb/pybind11/ALL_BUILD.vcxproj
quasardb/pybind11/ALL_BUILD.vcxproj.filters
quasardb/pybind11/INSTALL.vcxproj
quasardb/pybind11/INSTALL.vcxproj.filters
quasardb/pybind11/cmake_install.cmake
quasardb/pybind11/pybind11.sln
quasardb/pybind11/CMakeFiles/generate.stamp
quasardb/pybind11/CMakeFiles/generate.stamp.depend
quasardb/quasardb/__init__.pyi
quasardb/quasardb/_batch_column.pyi
quasardb/quasardb/_batch_inserter.pyi
quasardb/quasardb/_blob.pyi
quasardb/quasardb/_cluster.pyi
quasardb/quasardb/_continuous.pyi
quasardb/quasardb/_double.pyi
quasardb/quasardb/_entry.pyi
quasardb/quasardb/_error.pyi
quasardb/quasardb/_integer.pyi
quasardb/quasardb/_node.pyi
quasardb/quasardb/_options.pyi
quasardb/quasardb/_perf.pyi
quasardb/quasardb/_properties.pyi
quasardb/quasardb/_query.pyi
quasardb/quasardb/_reader.pyi
quasardb/quasardb/_retry.pyi
quasardb/quasardb/_string.pyi
quasardb/quasardb/_table.pyi
quasardb/quasardb/_tag.pyi
quasardb/quasardb/_timestamp.pyi
quasardb/quasardb/_writer.pyi
quasardb/quasardb/metrics/__init__.pyi
quasardb/range-v3/ALL_BUILD.vcxproj
quasardb-3.14.2.post0.dist-info/licenses/LICENSE.md
quasardb-3.14.2.post0.dist-info/METADATA
quasardb-3.14.2.post0.dist-info/WHEEL
quasardb-3.14.2.post0.dist-info/top_level.txt
quasardb-3.14.2.post0.dist-info/RECORD
